<?xml version="1.0" encoding="UTF-8" standalone="yes"?>
<data>
  <loc>https://www.st-claire.eu/erreurs-eviter-voyage-vietnam</loc>
  <lastmod>2026-06-02T05:52:00+00:00</lastmod>
  <loc>https://chefdodo.com/top-15-des-meilleures-specialites-de-la-cuisine-de-namur/</loc>
  <lastmod>2026-06-01T10:07:05+01:00</lastmod>
  <image:image>
    <image:loc>https://chefdodo.com/wp-content/uploads/2026/06/image.jpeg</image:loc>
    <image:loc>https://chefdodo.com/wp-content/uploads/2026/06/image-1.jpeg</image:loc>
    <image:loc>https://chefdodo.com/wp-content/uploads/2026/06/image.jpg</image:loc>
    <image:loc>https://chefdodo.com/wp-content/uploads/2026/06/8affdaef7e10a622bb5dd6ddec577622c2440fa1.jpg</image:loc>
  </image:image>
  <loc>https://chefdodo.com/recette-diots/</loc>
  <lastmod>2026-06-01T10:00:49+01:00</lastmod>
  <image:image>
    <image:loc>https://chefdodo.com/wp-content/uploads/2026/06/output1.png</image:loc>
  </image:image>
  <loc>https://chefdodo.com/recette-civet-de-sanglier/</loc>
  <lastmod>2026-05-31T09:59:53+01:00</lastmod>
  <image:image>
    <image:loc>https://chefdodo.com/wp-content/uploads/2026/05/output1-17.png</image:loc>
  </image:image>
  <loc>https://www.st-claire.eu/recette-flan-patissier-grand-mere</loc>
  <lastmod>2026-06-01T09:28:09+00:00</lastmod>
  <loc>https://www.st-claire.eu/tarte-tatin-grand-mere-recette-traditionnelle</loc>
  <lastmod>2026-05-31T09:17:12+00:00</lastmod>
  <loc>https://www.st-claire.eu/tomates-farcies-riz-grand-mere</loc>
  <lastmod>2026-05-31T05:50:00+00:00</lastmod>
  <loc>https://www.st-claire.eu/salade-pomme-terre-recette-grand-mere</loc>
  <lastmod>2026-05-30T09:07:10+00:00</lastmod>
  <loc>https://chefdodo.com/pop-corn-micro-onde/</loc>
  <lastmod>2026-05-29T10:00:43+01:00</lastmod>
  <image:image>
    <image:loc>https://chefdodo.com/wp-content/uploads/2026/05/output1-16.png</image:loc>
  </image:image>
  <loc>https://www.st-claire.eu/parmentier-canard-grand-mere</loc>
  <lastmod>2026-05-29T09:09:38+00:00</lastmod>
</data>